{
  "persons": [
    {
      "name": "Arto Hellas",
      "phone": "040-123456",
      "id": 1
    },
    {
      "name": "Ada Lovelace",
      "phone": "39-44-5323523",
      "id": 2
    },
    {
      "name": "Dan Abramov",
      "phone": "12-43-234345",
      "id": 3
    },
    {
      "name": "Mary Poppendieck",
      "phone": "39-23-6423122",
      "id": 4
    },
    {
      "name": "Cora Day",
      "phone": "555-4545",
      "id": 7
    },
    {
      "name": "Arlo Dee",
      "phone": "144-7886",
      "id": 8
    },
    {
      "name": "Dana Fine",
      "phone": "114-7878",
      "id": 9
    },
    {
      "name": "Zora Style",
      "phone": "243-5961",
      "id": 10
    },
    {
      "name": "Jonah Wier",
      "phone": "455-8887",
      "id": 14
    },
    {
      "name": "Missy Lowe",
      "phone": "256-889-7545",
      "id": 15
    },
    {
      "name": "Zora Day",
      "phone": "555-4546",
      "id": 16
    }
  ]
}